{
  "game_type": 3,
  "board_size": 15,
  "winner": 2,
  "total_time_ms": 49920,
  "game_id": "20250530_153930_0",
  "moves": [112, 92, 199, 73, 57, 140, 151, 26, 34, 162, 50, 147, 36, 179, 19, 18, 219, 16, 76, 160, 47, 195, 22, 94, 4, 188, 35, 134, 143, 132, 83, 146, 1, 174],
  "policies": [
    [0, 0, 0, 0, 0, 0, 0, 0, 0, 0, 0, 0, 0, 0, 0, 0, 0, 0, 0, 0, 0, 0, 0, 0, 0, 0, 0, 0, 0, 0, 0, 0, 0, 0, 0, 0, 0, 0, 0, 0, 0, 0, 0, 0, 0, 0, 0, 0, 0, 0, 0, 0, 0, 0, 0, 0, 0, 0, 0, 0, 0, 0, 0, 0, 0, 0, 0, 0, 0, 0, 0, 0, 0, 0, 0, 0, 0, 0, 0, 0, 0, 0, 0, 0, 0, 0, 0, 0, 0, 0, 0, 0, 0, 0, 0, 0, 0, 0, 0, 0, 0, 0, 0, 0, 0, 0, 0, 0, 0, 0, 0, 0, 1, 0, 0, 0, 0, 0, 0, 0, 0, 0, 0, 0, 0, 0, 0, 0, 0, 0, 0, 0, 0, 0, 0, 0, 0, 0, 0, 0, 0, 0, 0, 0, 0, 0, 0, 0, 0, 0, 0, 0, 0, 0, 0, 0, 0, 0, 0, 0, 0, 0, 0, 0, 0, 0, 0, 0, 0, 0, 0, 0, 0, 0, 0, 0, 0, 0, 0, 0, 0, 0, 0, 0, 0, 0, 0, 0, 0, 0, 0, 0, 0, 0, 0, 0, 0, 0, 0, 0, 0, 0, 0, 0, 0, 0, 0, 0, 0, 0, 0, 0, 0, 0, 0, 0, 0, 0, 0, 0, 0, 0, 0, 0, 0],
    [],
    [],
    [],
    [],
    [],
    [],
    [],
    [],
    [],
    [],
    [],
    [],
    [],
    [],
    [],
    [],
    [],
    [],
    [],
    [],
    [],
    [],
    [],
    [],
    [],
    [],
    [],
    [],
    [],
    [],
    [],
    [],
    []
  ]
}
