{
  "game_type": 3,
  "board_size": 15,
  "winner": 2,
  "total_time_ms": 150651,
  "game_id": "20250530_154551_0",
  "moves": [112, 109, 62, 88, 57, 173, 179, 67, 92, 42, 123, 130, 119, 162, 77, 43, 211, 153, 41, 210, 155, 10, 34, 84, 55, 135, 174, 22, 35, 78, 25, 49, 5, 89, 209, 87, 73, 146, 141, 144, 65, 66, 206, 140, 145, 214, 98, 58, 188, 133, 16, 124, 152, 19, 189, 48, 148, 69, 208, 217, 116, 60, 106, 122, 81, 190, 75, 56, 12, 166, 38, 200, 196, 85, 139, 68, 21, 71, 181, 70],
  "policies": [
    [0, 0, 0, 0, 0, 0, 0, 0, 0, 0, 0, 0, 0, 0, 0, 0, 0, 0, 0, 0, 0, 0, 0, 0, 0, 0, 0, 0, 0, 0, 0, 0, 0, 0, 0, 0, 0, 0, 0, 0, 0, 0, 0, 0, 0, 0, 0, 0, 0, 0, 0, 0, 0, 0, 0, 0, 0, 0, 0, 0, 0, 0, 0, 0, 0, 0, 0, 0, 0, 0, 0, 0, 0, 0, 0, 0, 0, 0, 0, 0, 0, 0, 0, 0, 0, 0, 0, 0, 0, 0, 0, 0, 0, 0, 0, 0, 0, 0, 0, 0, 0, 0, 0, 0, 0, 0, 0, 0, 0, 0, 0, 0, 1, 0, 0, 0, 0, 0, 0, 0, 0, 0, 0, 0, 0, 0, 0, 0, 0, 0, 0, 0, 0, 0, 0, 0, 0, 0, 0, 0, 0, 0, 0, 0, 0, 0, 0, 0, 0, 0, 0, 0, 0, 0, 0, 0, 0, 0, 0, 0, 0, 0, 0, 0, 0, 0, 0, 0, 0, 0, 0, 0, 0, 0, 0, 0, 0, 0, 0, 0, 0, 0, 0, 0, 0, 0, 0, 0, 0, 0, 0, 0, 0, 0, 0, 0, 0, 0, 0, 0, 0, 0, 0, 0, 0, 0, 0, 0, 0, 0, 0, 0, 0, 0, 0, 0, 0, 0, 0, 0, 0, 0, 0, 0, 0],
    [],
    [],
    [],
    [],
    [],
    [],
    [],
    [],
    [],
    [],
    [],
    [],
    [],
    [],
    [],
    [],
    [],
    [],
    [],
    [],
    [],
    [],
    [],
    [],
    [],
    [],
    [],
    [],
    [],
    [],
    [],
    [],
    [],
    [],
    [],
    [],
    [],
    [],
    [],
    [],
    [],
    [],
    [],
    [],
    [],
    [],
    [],
    [],
    [],
    [],
    [],
    [],
    [],
    [],
    [],
    [],
    [],
    [],
    [],
    [],
    [],
    [],
    [],
    [],
    [],
    [],
    [],
    [],
    [],
    [],
    [],
    [],
    [],
    [],
    [],
    [],
    [],
    [],
    []
  ]
}
